kstprocess/__init__.py
kstprocess/dialog/__init__.py
kstprocess/dialog/policy_module.py
kstprocess/dialog/postprocess.py
kstprocess/dialog/prompt_rule_module.py
kstprocess/dialog/util.py
kstprocess/preferenceDataConstruct/OnlinePreferenceConstructPipeline.py
kstprocess/preferenceDataConstruct/QuestioningPreferencePipeline.py
kstprocess/preferenceDataConstruct/__init__.py
kstprocess/preferenceDataConstruct/thinkmodeDataConstructPipeline.py
kstprocess/preferenceDataConstruct/util.py
kstprocess/preferenceDataConstruct/lib/__init__.py
kstprocess/preferenceDataConstruct/lib/action_predict.py
kstprocess/preferenceDataConstruct/lib/client_server.py
kstprocess/preferenceDataConstruct/lib/prompt_lab.py
kstprocess/preferenceDataConstruct/lib/util.py
kstprocess/preferenceDataConstruct/lib/儿科dpo构建piplinedemo.py
kstprocess/qadatabaseConstruct/__init__.py
kstprocess/qadatabaseConstruct/duplication_data.py
kstprocess/qadatabaseConstruct/generate_answer_by_llm.py
kstprocess/qadatabaseConstruct/rewrite_answer_by_trainedModel.py
kstprocess/qadatabaseConstruct/util.py
kstprocess/simTrainDatasetsConstruct/__init__.py
kstprocess/simTrainDatasetsConstruct/build_embbase_annoy.py
kstprocess/simTrainDatasetsConstruct/build_test_data.py
kstprocess/simTrainDatasetsConstruct/duplication_trainData.py
kstprocess/test/__init__.py
kstprocess/test/test_for_badcase.py
kstprocess/test/test_for_preference.py
kstprocess/util/__init__.py
kstprocess/util/annotation_util.py
kstprocess/util/format_convert.py
kstprocess/util/llm_server.py
kstprocess/util/util.py
kstprocess/util/analysis/__init__.py
kstprocess/util/analysis/analysis_func.py
kstprocess/util/postprocess/__init__.py
kstprocess/util/postprocess/action_util.py
kstprocess/util/postprocess/duplication_util.py
kstprocess/util/postprocess/preference_data_postprocess.py
kstprocess/util/preprocess/__init__.py
kstprocess/util/preprocess/preprocess_xlsx.py
kstprocess/util/preprocess/sft_datapreprocess.py
kstprocess-0.3.17.dist-info/METADATA
kstprocess-0.3.17.dist-info/WHEEL
kstprocess-0.3.17.dist-info/top_level.txt
kstprocess-0.3.17.dist-info/RECORD
