Metadata-Version: 2.4
Name: kstprocess
Version: 0.3.17
Summary: dataprocess for dialog robot
Author: kevin
Author-email: kevin.yuzhenjie@gmail.com
Classifier: Programming Language :: Python :: 3
Classifier: License :: OSI Approved :: MIT License
Classifier: Operating System :: OS Independent
Requires-Python: >=3.6
Dynamic: author
Dynamic: author-email
Dynamic: classifier
Dynamic: description
Dynamic: description-content-type
Dynamic: requires-python
Dynamic: summary
